xmcp_server_exepython/__init__.py
xmcp_server_exepython/__main__.py
xmcp_server_exepython/server.py
xmcp_server_exepython-0.1.0.dist-info/METADATA
xmcp_server_exepython-0.1.0.dist-info/WHEEL
xmcp_server_exepython-0.1.0.dist-info/entry_points.txt
xmcp_server_exepython-0.1.0.dist-info/RECORD
