Metadata-Version: 2.4
Name: xmcp-server-exepython
Version: 0.1.0
Summary: 本地执行python代码MCP服务
Requires-Python: >=3.10
Requires-Dist: mcp[cli]>=1.9.4
